skribble/__init__.py
skribble/auth.py
skribble/client.py
skribble/config.py
skribble/exceptions.py
skribble/resources/__init__.py
skribble/resources/documents.py
skribble/resources/monitoring.py
skribble/resources/report.py
skribble/resources/seals.py
skribble/resources/sendto.py
skribble/resources/signature_requests.py
skribble/resources/user.py
skribble-0.1.5.dist-info/licenses/LICENSE
skribble-0.1.5.dist-info/METADATA
skribble-0.1.5.dist-info/WHEEL
skribble-0.1.5.dist-info/top_level.txt
skribble-0.1.5.dist-info/RECORD
