Metadata-Version: 2.4
Name: skribble
Version: 0.1.5
Summary: Official-spec Skribble API v2 SDK (built from Skribble Postman collection)
Author-email: Farzam Mehdi <162793033+iamfarzam@users.noreply.github.com>
License: MIT
Project-URL: Homepage, https://github.com/iamfarzam/skribble-sdk
Project-URL: Source, https://github.com/iamfarzam/skribble-sdk
Requires-Python: >=3.9
License-File: LICENSE
Requires-Dist: requests>=2.31.0
Requires-Dist: redis>=5.0.0
Dynamic: license-file
